{
  "bots": [
    {
      "fileName": "hello-bot.ts",
      "botId": "hello-bot",
      "owner": "reef",
      "publisher": "Reef Examples",
      "approvedVersion": "1.0.0",
      "status": "draft"
    },
    {
      "fileName": "lifecycle-safe-market-maker.ts",
      "botId": "lifecycle-safe-market-maker",
      "owner": "reef",
      "publisher": "Reef Examples",
      "approvedVersion": "1.0.0",
      "status": "draft"
    },
    {
      "fileName": "multi-symbol-strategy-bot.ts",
      "botId": "multi-symbol-strategy",
      "owner": "reef",
      "publisher": "Reef Examples",
      "approvedVersion": "1.0.0",
      "status": "draft"
    },
    {
      "fileName": "refreshing-market-maker.ts",
      "botId": "refreshing-market-maker",
      "owner": "reef",
      "publisher": "Reef Examples",
      "approvedVersion": "1.0.0",
      "status": "draft"
    },
    {
      "fileName": "simple-market-maker.ts",
      "botId": "simple-market-maker",
      "owner": "reef",
      "publisher": "Reef Examples",
      "approvedVersion": "1.0.0",
      "status": "draft"
    }
  ]
}
