{
  "mode": "dry-run",
  "pass": true,
  "pathId": "P2_SETTLEMENT_BREAK_REPAIR",
  "scenarioRunId": "p2-settlement-break-repair-golden",
  "seed": 424243,
  "baseUrl": "http://localhost:8080",
  "seedRequests": [
    {
      "method": "POST",
      "path": "/reference/instruments",
      "url": "http://localhost:8080/reference/instruments",
      "headers": {
        "X-Reef-Internal-Route": "true"
      },
      "payload": {
        "instrumentId": "XYZ",
        "symbol": "XYZ"
      }
    },
    {
      "method": "POST",
      "path": "/reference/participants",
      "url": "http://localhost:8080/reference/participants",
      "headers": {
        "X-Reef-Internal-Route": "true"
      },
      "payload": {
        "name": "BUY_SIDE_1",
        "participantId": "BUY_SIDE_1"
      }
    },
    {
      "method": "POST",
      "path": "/reference/participants",
      "url": "http://localhost:8080/reference/participants",
      "headers": {
        "X-Reef-Internal-Route": "true"
      },
      "payload": {
        "name": "SELL_SIDE_1",
        "participantId": "SELL_SIDE_1"
      }
    },
    {
      "method": "POST",
      "path": "/reference/accounts",
      "url": "http://localhost:8080/reference/accounts",
      "headers": {
        "X-Reef-Internal-Route": "true"
      },
      "payload": {
        "accountId": "BUY_SIDE_1_MAIN",
        "participantId": "BUY_SIDE_1"
      }
    },
    {
      "method": "POST",
      "path": "/reference/accounts",
      "url": "http://localhost:8080/reference/accounts",
      "headers": {
        "X-Reef-Internal-Route": "true"
      },
      "payload": {
        "accountId": "SELL_SIDE_1_MAIN",
        "participantId": "SELL_SIDE_1"
      }
    },
    {
      "method": "POST",
      "path": "/auth/roles",
      "url": "http://localhost:8080/auth/roles",
      "headers": {
        "X-Reef-Internal-Route": "true"
      },
      "payload": {
        "permissions": "order.submit,order.cancel,order.modify",
        "roleId": "order_trader"
      }
    },
    {
      "method": "POST",
      "path": "/auth/actor-roles",
      "url": "http://localhost:8080/auth/actor-roles",
      "headers": {
        "X-Reef-Internal-Route": "true"
      },
      "payload": {
        "actorId": "BUY_SIDE_1_MAIN",
        "roleId": "order_trader"
      }
    },
    {
      "method": "POST",
      "path": "/auth/actor-roles",
      "url": "http://localhost:8080/auth/actor-roles",
      "headers": {
        "X-Reef-Internal-Route": "true"
      },
      "payload": {
        "actorId": "SELL_SIDE_1_MAIN",
        "roleId": "order_trader"
      }
    }
  ],
  "requests": [
    {
      "sequence": 1,
      "command": "SubmitOrder",
      "method": "POST",
      "path": "/api/v1/orders/submit",
      "url": "http://localhost:8080/api/v1/orders/submit",
      "headers": {
        "Idempotency-Key": "p2_settlement_break_repair-cmd-001",
        "X-Client-Id": "scenario-smoke-1",
        "X-Correlation-Id": "p2_settlement_break_repair-trace-001"
      },
      "payload": {
        "accountId": "BUY_SIDE_1_MAIN",
        "actorId": "BUY_SIDE_1_MAIN",
        "actorType": "BOT",
        "causationId": "p2_settlement_break_repair-cause-001",
        "clientOrderId": "p2_settlement_break_repair-ord-001",
        "commandId": "p2_settlement_break_repair-cmd-001",
        "correlationId": "p2_settlement_break_repair-corr-001",
        "currency": "USD",
        "instrumentId": "XYZ",
        "limitPrice": "150000000000",
        "occurredAt": "2026-03-14T18:00:01Z",
        "orderId": "p2_settlement_break_repair-ord-001",
        "orderType": "LIMIT",
        "participantId": "BUY_SIDE_1",
        "quantityUnits": "1000",
        "runId": "p2-settlement-break-repair-golden",
        "runKind": "scenario",
        "scenarioId": "P2_SETTLEMENT_BREAK_REPAIR",
        "scenarioRunId": "p2-settlement-break-repair-golden",
        "seed": "424243",
        "side": "BUY",
        "timeInForce": "DAY",
        "traceId": "p2_settlement_break_repair-trace-001",
        "venueSessionId": "P2_SETTLEMENT_BREAK_REPAIR"
      }
    },
    {
      "sequence": 2,
      "command": "SubmitOrder",
      "method": "POST",
      "path": "/api/v1/orders/submit",
      "url": "http://localhost:8080/api/v1/orders/submit",
      "headers": {
        "Idempotency-Key": "p2_settlement_break_repair-cmd-002",
        "X-Client-Id": "scenario-smoke-2",
        "X-Correlation-Id": "p2_settlement_break_repair-trace-002"
      },
      "payload": {
        "accountId": "SELL_SIDE_1_MAIN",
        "actorId": "SELL_SIDE_1_MAIN",
        "actorType": "BOT",
        "causationId": "p2_settlement_break_repair-cause-001",
        "clientOrderId": "p2_settlement_break_repair-ord-002",
        "commandId": "p2_settlement_break_repair-cmd-002",
        "correlationId": "p2_settlement_break_repair-corr-001",
        "currency": "USD",
        "instrumentId": "XYZ",
        "limitPrice": "150000000000",
        "occurredAt": "2026-03-14T18:00:02Z",
        "orderId": "p2_settlement_break_repair-ord-002",
        "orderType": "LIMIT",
        "participantId": "SELL_SIDE_1",
        "quantityUnits": "1000",
        "runId": "p2-settlement-break-repair-golden",
        "runKind": "scenario",
        "scenarioId": "P2_SETTLEMENT_BREAK_REPAIR",
        "scenarioRunId": "p2-settlement-break-repair-golden",
        "seed": "424243",
        "side": "SELL",
        "timeInForce": "DAY",
        "traceId": "p2_settlement_break_repair-trace-002",
        "venueSessionId": "P2_SETTLEMENT_BREAK_REPAIR"
      }
    }
  ]
}
